{
  "nodes": [
    {
      "parameters": {
        "rule": {
          "interval": [
            {
              "field": "hours",
              "hoursInterval": 6
            }
          ]
        }
      },
      "id": "021d3618-d28f-427f-a395-7f9138f6bdd4",
      "name": "Schedule Trigger",
      "type": "n8n-nodes-base.scheduleTrigger",
      "typeVersion": 1.1,
      "position": [
        -1040,
        272
      ]
    },
    {
      "parameters": {
        "method": "POST",
        "url": "http://host.docker.internal:8000/api/v1/start-crawl/wecandoo",
        "options": {}
      },
      "id": "5786dc51-55c6-4cb8-8f89-bab652a83caf",
      "name": "Start Crawl API",
      "type": "n8n-nodes-base.httpRequest",
      "typeVersion": 4.2,
      "position": [
        -848,
        272
      ]
    },
    {
      "parameters": {
        "conditions": {
          "options": {
            "caseSensitive": true,
            "leftValue": "",
            "typeValidation": "strict"
          },
          "conditions": [
            {
              "id": "check-status-code",
              "leftValue": "={{ $json.status }}",
              "rightValue": "started",
              "operator": {
                "type": "string",
                "operation": "equals"
              }
            }
          ],
          "combinator": "and"
        },
        "options": {}
      },
      "id": "d313c221-e6df-4083-9c0f-91c777984c23",
      "name": "Check API Response",
      "type": "n8n-nodes-base.if",
      "typeVersion": 2,
      "position": [
        -640,
        272
      ]
    },
    {
      "parameters": {
        "amount": 10
      },
      "id": "d7d1f115-2294-475b-81c0-1f3ef4856c58",
      "name": "Wait Before Check",
      "type": "n8n-nodes-base.wait",
      "typeVersion": 1.1,
      "position": [
        -448,
        176
      ],
      "webhookId": "cd3ff222-2b8f-400e-9558-b6afebb48271"
    },
    {
      "parameters": {
        "url": "=http://host.docker.internal:8000/api/v1/start-crawl/status/{{ $('Start Crawl API').item.json.task_id }}",
        "options": {}
      },
      "id": "44e9b0c4-f6b1-4bf9-9668-7aefd540151c",
      "name": "Check Status",
      "type": "n8n-nodes-base.httpRequest",
      "typeVersion": 4.2,
      "position": [
        -240,
        176
      ]
    },
    {
      "parameters": {
        "conditions": {
          "options": {
            "caseSensitive": true,
            "leftValue": "",
            "typeValidation": "strict",
            "version": 1
          },
          "conditions": [
            {
              "id": "check-failed",
              "leftValue": "={{ $json.status }}",
              "rightValue": "FAILURE",
              "operator": {
                "type": "string",
                "operation": "equals"
              }
            },
            {
              "id": "check-failed-alt",
              "leftValue": "={{ $json.status }}",
              "rightValue": "FAILED",
              "operator": {
                "type": "string",
                "operation": "equals"
              }
            }
          ],
          "combinator": "or"
        },
        "options": {}
      },
      "id": "2c2097e2-70ac-4531-b25b-37cdd9b41611",
      "name": "Is Failed?",
      "type": "n8n-nodes-base.if",
      "typeVersion": 2,
      "position": [
        -16,
        176
      ]
    },
    {
      "parameters": {
        "conditions": {
          "options": {
            "caseSensitive": true,
            "leftValue": "",
            "typeValidation": "strict"
          },
          "conditions": [
            {
              "id": "check-success",
              "leftValue": "={{ $json.status }}",
              "rightValue": "SUCCESS",
              "operator": {
                "type": "string",
                "operation": "equals"
              }
            }
          ],
          "combinator": "and"
        },
        "options": {}
      },
      "id": "90d1cb19-a0f7-4334-b6cc-02a112a530af",
      "name": "Is Success?",
      "type": "n8n-nodes-base.if",
      "typeVersion": 2,
      "position": [
        208,
        176
      ]
    },
    {
      "parameters": {
        "conditions": {
          "options": {
            "caseSensitive": true,
            "leftValue": "",
            "typeValidation": "strict"
          },
          "conditions": [
            {
              "id": "check-pending",
              "leftValue": "={{ $json.status }}",
              "rightValue": "PENDING",
              "operator": {
                "type": "string",
                "operation": "equals"
              }
            },
            {
              "id": "check-progress",
              "leftValue": "={{ $json.status }}",
              "rightValue": "PROGRESS",
              "operator": {
                "type": "string",
                "operation": "equals"
              }
            },
            {
              "id": "check-started",
              "leftValue": "={{ $json.status }}",
              "rightValue": "STARTED",
              "operator": {
                "type": "string",
                "operation": "equals"
              }
            }
          ],
          "combinator": "or"
        },
        "options": {}
      },
      "id": "a01a85ed-b847-435d-b9b6-e8f989840431",
      "name": "Is Pending/Progress?",
      "type": "n8n-nodes-base.if",
      "typeVersion": 2,
      "position": [
        432,
        176
      ]
    },
    {
      "parameters": {
        "assignments": {
          "assignments": [
            {
              "id": "success-log",
              "name": "message",
              "value": "=Crawl terminé avec succès! {{ $json.items_scraped }} items scrapés",
              "type": "string"
            },
            {
              "id": "task-id",
              "name": "task_id",
              "value": "={{ $('Start Crawl API').item.json.task_id }}",
              "type": "string"
            },
            {
              "id": "items",
              "name": "items_scraped",
              "value": "={{ $json.items_scraped || 0 }}",
              "type": "number"
            }
          ]
        },
        "options": {}
      },
      "id": "23503ebd-914a-458c-9e2a-9c52cd10a1b8",
      "name": "Success Log",
      "type": "n8n-nodes-base.set",
      "typeVersion": 3.3,
      "position": [
        208,
        16
      ]
    },
    {
      "parameters": {
        "assignments": {
          "assignments": [
            {
              "id": "error-log",
              "name": "message",
              "value": "=Crawl échoué: {{ $json.error_message || 'Erreur inconnue' }}",
              "type": "string"
            },
            {
              "id": "task-id-error",
              "name": "task_id",
              "value": "={{ $('Start Crawl API').item.json.task_id }}",
              "type": "string"
            }
          ]
        },
        "options": {}
      },
      "id": "3b6c414b-c1f2-4943-ad15-f2785fdd6cc8",
      "name": "Error Log",
      "type": "n8n-nodes-base.set",
      "typeVersion": 3.3,
      "position": [
        -16,
        16
      ]
    },
    {
      "parameters": {
        "assignments": {
          "assignments": [
            {
              "id": "unknown-log",
              "name": "message",
              "value": "=Statut inconnu: {{ $json.status }}",
              "type": "string"
            }
          ]
        },
        "options": {}
      },
      "id": "b9d3fb69-ba08-4210-920a-6db6093ff377",
      "name": "Unknown Status Log",
      "type": "n8n-nodes-base.set",
      "typeVersion": 3.3,
      "position": [
        432,
        16
      ]
    }
  ],
  "connections": {
    "Schedule Trigger": {
      "main": [
        [
          {
            "node": "Start Crawl API",
            "type": "main",
            "index": 0
          }
        ]
      ]
    },
    "Start Crawl API": {
      "main": [
        [
          {
            "node": "Check API Response",
            "type": "main",
            "index": 0
          }
        ]
      ]
    },
    "Check API Response": {
      "main": [
        [
          {
            "node": "Wait Before Check",
            "type": "main",
            "index": 0
          }
        ],
        [
          {
            "node": "Error Log",
            "type": "main",
            "index": 0
          }
        ]
      ]
    },
    "Wait Before Check": {
      "main": [
        [
          {
            "node": "Check Status",
            "type": "main",
            "index": 0
          }
        ]
      ]
    },
    "Check Status": {
      "main": [
        [
          {
            "node": "Is Failed?",
            "type": "main",
            "index": 0
          }
        ]
      ]
    },
    "Is Failed?": {
      "main": [
        [
          {
            "node": "Error Log",
            "type": "main",
            "index": 0
          }
        ],
        [
          {
            "node": "Is Success?",
            "type": "main",
            "index": 0
          }
        ]
      ]
    },
    "Is Success?": {
      "main": [
        [
          {
            "node": "Success Log",
            "type": "main",
            "index": 0
          }
        ],
        [
          {
            "node": "Is Pending/Progress?",
            "type": "main",
            "index": 0
          }
        ]
      ]
    },
    "Is Pending/Progress?": {
      "main": [
        [
          {
            "node": "Wait Before Check",
            "type": "main",
            "index": 0
          }
        ],
        [
          {
            "node": "Unknown Status Log",
            "type": "main",
            "index": 0
          }
        ]
      ]
    }
  },
  "pinData": {},
  "meta": {
    "templateCredsSetupCompleted": true,
    "instanceId": "e2217d3e4e120c6a3372a1890f03e232b35ad659d71f7a62501a4ee204a3e66d"
  }
}